scalabis/__init__.py
scalabis/comparisons.py
scalabis-1.1.dist-info/METADATA
scalabis-1.1.dist-info/WHEEL
scalabis-1.1.dist-info/top_level.txt
scalabis-1.1.dist-info/RECORD
