Metadata-Version: 2.1
Name: scalabis
Version: 1.1
Summary: A Python3 module for fast & easy sequence comparison.
Home-page: https://github.com/afombravo/scalabis
Author: Afonso M Bravo
Author-email: <afonsombravo@hotmail.com>
License: UNKNOWN
Keywords: sequence,mismatch,comparison
Platform: UNKNOWN
Classifier: Development Status :: 6 - Mature
Classifier: Intended Audience :: Science/Research
Classifier: Programming Language :: Python :: 3
Classifier: Operating System :: OS Independent
